MANIFEST.in
README.md
_triez.c
config.h
setup.cfg
setup.py
trie.c
trie.h
triez.py
pyctrie.egg-info/PKG-INFO
pyctrie.egg-info/SOURCES.txt
pyctrie.egg-info/dependency_links.txt
pyctrie.egg-info/top_level.txt