Metadata-Version: 1.1
Name: pyctrie
Version: 0.1
Summary: Fast, pure C trie
Home-page: http://bitbucket.org/sumerc/pyctrie/
Author: Sumer Cip
Author-email: sumerc@gmail.com
License: MIT
Download-URL: http://bitbucket.org/sumerc/pyctrie//pyctrie-0.1.tar.gz
Keywords: tree trie data structure dictionary
Platform: UNKNOWN
Classifier: Development Status :: 5 - Production/Stable
Classifier: Environment :: Console
Classifier: Intended Audience :: Developers
Classifier: License :: OSI Approved :: MIT License
Classifier: Programming Language :: Python
Classifier: Programming Language :: Python :: 2
Classifier: Programming Language :: Python :: 2.6
Classifier: Programming Language :: Python :: 2.7
Classifier: Programming Language :: Python :: 3.1
Classifier: Programming Language :: Python :: 3.2
Classifier: Programming Language :: Python :: 3.3
Classifier: Programming Language :: Python :: 3.4
Classifier: Programming Language :: Python :: Implementation :: CPython
Classifier: Operating System :: OS Independent
Classifier: Topic :: Software Development :: Libraries
Classifier: Topic :: Software Development :: Libraries :: Python Modules
